{"meta":{"name":"react-med-checklist","description":"react-med-checklist","github":"https://github.com/EBSCOIS/react-med-checklist/","version":"1.0.8"},"usage":[],"deps":[{"uri":"#","displayName":"react-med-extensions","version":{"status":"ok","str":"^1.0.51"},"description":""},{"uri":"#","displayName":"electrode-archetype-ebsco","version":{"status":"ok","str":"^1.0.7"},"description":"[dev]"},{"uri":"#","displayName":"electrode-archetype-react-component","version":{"status":"ok","str":"^1.0.0"},"description":"[dev]"},{"uri":"#","displayName":"electrode-archetype-react-component-dev","version":{"status":"ok","str":"^1.0.0"},"description":"[dev]"},{"uri":"#","displayName":"gulp","version":{"status":"ok","str":"^3.9.1"},"description":"[dev]"},{"uri":"#","displayName":"phantomjs","version":{"status":"ok","str":"^2.1.7"},"description":"[dev]"}]}